ms5803py/__init__.py
ms5803py/ms5803.py
ms5803py/sensor.py
ms5803py-1.0.0.dist-info/LICENSE
ms5803py-1.0.0.dist-info/METADATA
ms5803py-1.0.0.dist-info/WHEEL
ms5803py-1.0.0.dist-info/top_level.txt
ms5803py-1.0.0.dist-info/RECORD
