Metadata-Version: 2.1
Name: ms5803py
Version: 1.0.0
Summary: Python library for MS5803-14BA pressure sensor for Raspberry Pi over i2c
Home-page: https://github.com/NickCrews/ms5803py
Author: Nick Crews
Author-email: nicholas.b.crews@gmail.com
License: MIT
Platform: UNKNOWN
Classifier: Programming Language :: Python :: 3
Classifier: Topic :: Scientific/Engineering
Classifier: Topic :: Utilities
Classifier: Intended Audience :: Developers
Classifier: Intended Audience :: Education
Classifier: Intended Audience :: End Users/Desktop
Classifier: Intended Audience :: Science/Research
Classifier: Operating System :: OS Independent
Classifier: License :: OSI Approved :: MIT License
